geebap/__init__.py
geebap/bap.py
geebap/cloud_mask.py
geebap/date.py
geebap/expgen.py
geebap/expressions.py
geebap/filters.py
geebap/functions.py
geebap/indices.py
geebap/masks.py
geebap/satcol.py
geebap/scores.py
geebap/season.py
geebap/sites.py
geebap/tests/__init__.py
geebap/tests/test_bap.py
geebap/tests/test_sites.py
geebap-0.0.3.dist-info/DESCRIPTION.rst
geebap-0.0.3.dist-info/METADATA
geebap-0.0.3.dist-info/RECORD
geebap-0.0.3.dist-info/WHEEL
geebap-0.0.3.dist-info/metadata.json
geebap-0.0.3.dist-info/top_level.txt
