Metadata-Version: 2.0
Name: geebap
Version: 0.0.3
Summary: Generate a "Best Available Pixel (BAP)" composite in Google Earth Engine (GEE)
Home-page: UNKNOWN
Author: Rodrigo E. Principe
Author-email: rprincipe@ciefap.org.ar
License: GNU
Keywords: google earth engine raster image processing gis satelite
Platform: UNKNOWN
Classifier: Programming Language :: Python :: 2
Classifier: Programming Language :: Python :: 2.7
Requires-Dist: requests
Requires-Dist: simpleeval
Requires-Dist: numpy
Provides-Extra: dev
Provides-Extra: docs
Provides-Extra: testing
